{
  "input": {
    "schema": "tropical_program_2",
    "name": "sequencer_demo",
    "body": {
      "op": "block",
      "decls": [
        {
          "op": "instanceDecl",
          "name": "clk",
          "program": "Clock",
          "inputs": {
            "freq": 4,
            "ratios_in": [
              1
            ]
          }
        },
        {
          "op": "instanceDecl",
          "name": "seq",
          "program": "Sequencer",
          "inputs": {
            "clock": {
              "op": "ref",
              "instance": "clk",
              "output": "output"
            },
            "values": [
              110,
              138.59,
              164.81,
              220,
              261.63,
              329.63,
              220,
              164.81
            ]
          },
          "type_args": {
            "N": 8
          }
        },
        {
          "op": "instanceDecl",
          "name": "osc",
          "program": "BlepSaw",
          "inputs": {
            "freq": {
              "op": "ref",
              "instance": "seq",
              "output": "value"
            }
          }
        }
      ],
      "assigns": [],
      "value": null
    },
    "audio_outputs": [
      {
        "instance": "osc",
        "output": "saw"
      }
    ]
  },
  "expected_plan": {
    "schema": "tropical_plan_4",
    "config": {
      "sampleRate": 44100
    },
    "state_init": [
      0,
      0,
      0
    ],
    "register_names": [
      "seq_step",
      "osc_phase",
      "seq_prev_clock"
    ],
    "register_types": [
      "int",
      "float",
      "float"
    ],
    "array_slot_names": [],
    "outputs": [
      0
    ],
    "instructions": [
      {
        "tag": "Mul",
        "dst": 0,
        "args": [
          {
            "kind": "const",
            "val": 2,
            "scalar_type": "float"
          },
          {
            "kind": "state_reg",
            "slot": 1,
            "scalar_type": "float"
          }
        ],
        "loop_count": 1,
        "strides": [],
        "result_type": "float"
      },
      {
        "tag": "Sub",
        "dst": 1,
        "args": [
          {
            "kind": "reg",
            "slot": 0,
            "scalar_type": "float"
          },
          {
            "kind": "const",
            "val": 1,
            "scalar_type": "float"
          }
        ],
        "loop_count": 1,
        "strides": [],
        "result_type": "float"
      },
      {
        "tag": "Pack",
        "dst": 0,
        "args": [
          {
            "kind": "const",
            "val": 110,
            "scalar_type": "float"
          },
          {
            "kind": "const",
            "val": 138.59,
            "scalar_type": "float"
          },
          {
            "kind": "const",
            "val": 164.81,
            "scalar_type": "float"
          },
          {
            "kind": "const",
            "val": 220,
            "scalar_type": "float"
          },
          {
            "kind": "const",
            "val": 261.63,
            "scalar_type": "float"
          },
          {
            "kind": "const",
            "val": 329.63,
            "scalar_type": "float"
          },
          {
            "kind": "const",
            "val": 220,
            "scalar_type": "float"
          },
          {
            "kind": "const",
            "val": 164.81,
            "scalar_type": "float"
          }
        ],
        "loop_count": 1,
        "strides": [],
        "result_type": "float"
      },
      {
        "tag": "Index",
        "dst": 2,
        "args": [
          {
            "kind": "array_reg",
            "slot": 0
          },
          {
            "kind": "state_reg",
            "slot": 0,
            "scalar_type": "int"
          }
        ],
        "loop_count": 1,
        "strides": [],
        "result_type": "float"
      },
      {
        "tag": "Div",
        "dst": 3,
        "args": [
          {
            "kind": "reg",
            "slot": 2,
            "scalar_type": "float"
          },
          {
            "kind": "rate",
            "scalar_type": "float"
          }
        ],
        "loop_count": 1,
        "strides": [],
        "result_type": "float"
      },
      {
        "tag": "Less",
        "dst": 4,
        "args": [
          {
            "kind": "state_reg",
            "slot": 1,
            "scalar_type": "float"
          },
          {
            "kind": "reg",
            "slot": 3,
            "scalar_type": "float"
          }
        ],
        "loop_count": 1,
        "strides": [],
        "result_type": "bool"
      },
      {
        "tag": "Div",
        "dst": 5,
        "args": [
          {
            "kind": "state_reg",
            "slot": 1,
            "scalar_type": "float"
          },
          {
            "kind": "reg",
            "slot": 3,
            "scalar_type": "float"
          }
        ],
        "loop_count": 1,
        "strides": [],
        "result_type": "float"
      },
      {
        "tag": "Mul",
        "dst": 6,
        "args": [
          {
            "kind": "const",
            "val": 2,
            "scalar_type": "float"
          },
          {
            "kind": "reg",
            "slot": 5,
            "scalar_type": "float"
          }
        ],
        "loop_count": 1,
        "strides": [],
        "result_type": "float"
      },
      {
        "tag": "Mul",
        "dst": 7,
        "args": [
          {
            "kind": "reg",
            "slot": 5,
            "scalar_type": "float"
          },
          {
            "kind": "reg",
            "slot": 5,
            "scalar_type": "float"
          }
        ],
        "loop_count": 1,
        "strides": [],
        "result_type": "float"
      },
      {
        "tag": "Sub",
        "dst": 8,
        "args": [
          {
            "kind": "reg",
            "slot": 6,
            "scalar_type": "float"
          },
          {
            "kind": "reg",
            "slot": 7,
            "scalar_type": "float"
          }
        ],
        "loop_count": 1,
        "strides": [],
        "result_type": "float"
      },
      {
        "tag": "Sub",
        "dst": 9,
        "args": [
          {
            "kind": "reg",
            "slot": 8,
            "scalar_type": "float"
          },
          {
            "kind": "const",
            "val": 1,
            "scalar_type": "float"
          }
        ],
        "loop_count": 1,
        "strides": [],
        "result_type": "float"
      },
      {
        "tag": "Select",
        "dst": 10,
        "args": [
          {
            "kind": "reg",
            "slot": 4,
            "scalar_type": "bool"
          },
          {
            "kind": "reg",
            "slot": 9,
            "scalar_type": "float"
          },
          {
            "kind": "const",
            "val": 0,
            "scalar_type": "float"
          }
        ],
        "loop_count": 1,
        "strides": [],
        "result_type": "float"
      },
      {
        "tag": "Sub",
        "dst": 11,
        "args": [
          {
            "kind": "reg",
            "slot": 1,
            "scalar_type": "float"
          },
          {
            "kind": "reg",
            "slot": 10,
            "scalar_type": "float"
          }
        ],
        "loop_count": 1,
        "strides": [],
        "result_type": "float"
      },
      {
        "tag": "Sub",
        "dst": 12,
        "args": [
          {
            "kind": "const",
            "val": 1,
            "scalar_type": "float"
          },
          {
            "kind": "reg",
            "slot": 3,
            "scalar_type": "float"
          }
        ],
        "loop_count": 1,
        "strides": [],
        "result_type": "float"
      },
      {
        "tag": "Greater",
        "dst": 13,
        "args": [
          {
            "kind": "state_reg",
            "slot": 1,
            "scalar_type": "float"
          },
          {
            "kind": "reg",
            "slot": 12,
            "scalar_type": "float"
          }
        ],
        "loop_count": 1,
        "strides": [],
        "result_type": "bool"
      },
      {
        "tag": "Sub",
        "dst": 14,
        "args": [
          {
            "kind": "state_reg",
            "slot": 1,
            "scalar_type": "float"
          },
          {
            "kind": "const",
            "val": 1,
            "scalar_type": "float"
          }
        ],
        "loop_count": 1,
        "strides": [],
        "result_type": "float"
      },
      {
        "tag": "Div",
        "dst": 15,
        "args": [
          {
            "kind": "reg",
            "slot": 14,
            "scalar_type": "float"
          },
          {
            "kind": "reg",
            "slot": 3,
            "scalar_type": "float"
          }
        ],
        "loop_count": 1,
        "strides": [],
        "result_type": "float"
      },
      {
        "tag": "Mul",
        "dst": 16,
        "args": [
          {
            "kind": "reg",
            "slot": 15,
            "scalar_type": "float"
          },
          {
            "kind": "reg",
            "slot": 15,
            "scalar_type": "float"
          }
        ],
        "loop_count": 1,
        "strides": [],
        "result_type": "float"
      },
      {
        "tag": "Mul",
        "dst": 17,
        "args": [
          {
            "kind": "const",
            "val": 2,
            "scalar_type": "float"
          },
          {
            "kind": "reg",
            "slot": 15,
            "scalar_type": "float"
          }
        ],
        "loop_count": 1,
        "strides": [],
        "result_type": "float"
      },
      {
        "tag": "Add",
        "dst": 18,
        "args": [
          {
            "kind": "reg",
            "slot": 16,
            "scalar_type": "float"
          },
          {
            "kind": "reg",
            "slot": 17,
            "scalar_type": "float"
          }
        ],
        "loop_count": 1,
        "strides": [],
        "result_type": "float"
      },
      {
        "tag": "Add",
        "dst": 19,
        "args": [
          {
            "kind": "reg",
            "slot": 18,
            "scalar_type": "float"
          },
          {
            "kind": "const",
            "val": 1,
            "scalar_type": "float"
          }
        ],
        "loop_count": 1,
        "strides": [],
        "result_type": "float"
      },
      {
        "tag": "Select",
        "dst": 20,
        "args": [
          {
            "kind": "reg",
            "slot": 13,
            "scalar_type": "bool"
          },
          {
            "kind": "reg",
            "slot": 19,
            "scalar_type": "float"
          },
          {
            "kind": "const",
            "val": 0,
            "scalar_type": "float"
          }
        ],
        "loop_count": 1,
        "strides": [],
        "result_type": "float"
      },
      {
        "tag": "Sub",
        "dst": 21,
        "args": [
          {
            "kind": "reg",
            "slot": 11,
            "scalar_type": "float"
          },
          {
            "kind": "reg",
            "slot": 20,
            "scalar_type": "float"
          }
        ],
        "loop_count": 1,
        "strides": [],
        "result_type": "float"
      },
      {
        "tag": "Clamp",
        "dst": 22,
        "args": [
          {
            "kind": "reg",
            "slot": 21,
            "scalar_type": "float"
          },
          {
            "kind": "const",
            "val": -1,
            "scalar_type": "float"
          },
          {
            "kind": "const",
            "val": 1,
            "scalar_type": "float"
          }
        ],
        "loop_count": 1,
        "strides": [],
        "result_type": "float"
      },
      {
        "tag": "Add",
        "dst": 23,
        "args": [
          {
            "kind": "reg",
            "slot": 22,
            "scalar_type": "float"
          },
          {
            "kind": "const",
            "val": 0,
            "scalar_type": "float"
          }
        ],
        "loop_count": 1,
        "strides": [],
        "result_type": "float"
      },
      {
        "tag": "Mul",
        "dst": 24,
        "args": [
          {
            "kind": "tick",
            "scalar_type": "int"
          },
          {
            "kind": "const",
            "val": 4,
            "scalar_type": "float"
          }
        ],
        "loop_count": 1,
        "strides": [],
        "result_type": "float"
      },
      {
        "tag": "Div",
        "dst": 25,
        "args": [
          {
            "kind": "reg",
            "slot": 24,
            "scalar_type": "float"
          },
          {
            "kind": "rate",
            "scalar_type": "float"
          }
        ],
        "loop_count": 1,
        "strides": [],
        "result_type": "float"
      },
      {
        "tag": "Mod",
        "dst": 26,
        "args": [
          {
            "kind": "reg",
            "slot": 25,
            "scalar_type": "float"
          },
          {
            "kind": "const",
            "val": 1,
            "scalar_type": "float"
          }
        ],
        "loop_count": 1,
        "strides": [],
        "result_type": "float"
      },
      {
        "tag": "Add",
        "dst": 27,
        "args": [
          {
            "kind": "reg",
            "slot": 26,
            "scalar_type": "float"
          },
          {
            "kind": "const",
            "val": 1,
            "scalar_type": "float"
          }
        ],
        "loop_count": 1,
        "strides": [],
        "result_type": "float"
      },
      {
        "tag": "Mod",
        "dst": 28,
        "args": [
          {
            "kind": "reg",
            "slot": 27,
            "scalar_type": "float"
          },
          {
            "kind": "const",
            "val": 1,
            "scalar_type": "float"
          }
        ],
        "loop_count": 1,
        "strides": [],
        "result_type": "float"
      },
      {
        "tag": "Less",
        "dst": 29,
        "args": [
          {
            "kind": "reg",
            "slot": 28,
            "scalar_type": "float"
          },
          {
            "kind": "const",
            "val": 0.5,
            "scalar_type": "float"
          }
        ],
        "loop_count": 1,
        "strides": [],
        "result_type": "bool"
      },
      {
        "tag": "Mul",
        "dst": 30,
        "args": [
          {
            "kind": "reg",
            "slot": 29,
            "scalar_type": "bool"
          },
          {
            "kind": "const",
            "val": 1,
            "scalar_type": "float"
          }
        ],
        "loop_count": 1,
        "strides": [],
        "result_type": "float"
      },
      {
        "tag": "Clamp",
        "dst": 31,
        "args": [
          {
            "kind": "reg",
            "slot": 30,
            "scalar_type": "float"
          },
          {
            "kind": "const",
            "val": 0,
            "scalar_type": "float"
          },
          {
            "kind": "const",
            "val": 1,
            "scalar_type": "float"
          }
        ],
        "loop_count": 1,
        "strides": [],
        "result_type": "float"
      },
      {
        "tag": "Greater",
        "dst": 32,
        "args": [
          {
            "kind": "reg",
            "slot": 31,
            "scalar_type": "float"
          },
          {
            "kind": "const",
            "val": 0.5,
            "scalar_type": "float"
          }
        ],
        "loop_count": 1,
        "strides": [],
        "result_type": "bool"
      },
      {
        "tag": "LessEq",
        "dst": 33,
        "args": [
          {
            "kind": "state_reg",
            "slot": 2,
            "scalar_type": "float"
          },
          {
            "kind": "const",
            "val": 0.5,
            "scalar_type": "float"
          }
        ],
        "loop_count": 1,
        "strides": [],
        "result_type": "bool"
      },
      {
        "tag": "Mul",
        "dst": 34,
        "args": [
          {
            "kind": "reg",
            "slot": 32,
            "scalar_type": "bool"
          },
          {
            "kind": "reg",
            "slot": 33,
            "scalar_type": "bool"
          }
        ],
        "loop_count": 1,
        "strides": [],
        "result_type": "bool"
      },
      {
        "tag": "Add",
        "dst": 35,
        "args": [
          {
            "kind": "state_reg",
            "slot": 0,
            "scalar_type": "int"
          },
          {
            "kind": "reg",
            "slot": 34,
            "scalar_type": "bool"
          }
        ],
        "loop_count": 1,
        "strides": [],
        "result_type": "int"
      },
      {
        "tag": "Mod",
        "dst": 36,
        "args": [
          {
            "kind": "reg",
            "slot": 35,
            "scalar_type": "int"
          },
          {
            "kind": "const",
            "val": 8,
            "scalar_type": "int"
          }
        ],
        "loop_count": 1,
        "strides": [],
        "result_type": "int"
      },
      {
        "tag": "Add",
        "dst": 37,
        "args": [
          {
            "kind": "reg",
            "slot": 36,
            "scalar_type": "int"
          },
          {
            "kind": "const",
            "val": 0,
            "scalar_type": "int"
          }
        ],
        "loop_count": 1,
        "strides": [],
        "result_type": "int"
      },
      {
        "tag": "Add",
        "dst": 38,
        "args": [
          {
            "kind": "state_reg",
            "slot": 1,
            "scalar_type": "float"
          },
          {
            "kind": "reg",
            "slot": 3,
            "scalar_type": "float"
          }
        ],
        "loop_count": 1,
        "strides": [],
        "result_type": "float"
      },
      {
        "tag": "Mod",
        "dst": 39,
        "args": [
          {
            "kind": "reg",
            "slot": 38,
            "scalar_type": "float"
          },
          {
            "kind": "const",
            "val": 1,
            "scalar_type": "float"
          }
        ],
        "loop_count": 1,
        "strides": [],
        "result_type": "float"
      },
      {
        "tag": "Add",
        "dst": 40,
        "args": [
          {
            "kind": "reg",
            "slot": 39,
            "scalar_type": "float"
          },
          {
            "kind": "const",
            "val": 0,
            "scalar_type": "float"
          }
        ],
        "loop_count": 1,
        "strides": [],
        "result_type": "float"
      },
      {
        "tag": "Less",
        "dst": 41,
        "args": [
          {
            "kind": "reg",
            "slot": 28,
            "scalar_type": "float"
          },
          {
            "kind": "const",
            "val": 0.5,
            "scalar_type": "float"
          }
        ],
        "loop_count": 1,
        "strides": [],
        "result_type": "bool"
      },
      {
        "tag": "Mul",
        "dst": 42,
        "args": [
          {
            "kind": "reg",
            "slot": 41,
            "scalar_type": "bool"
          },
          {
            "kind": "const",
            "val": 1,
            "scalar_type": "float"
          }
        ],
        "loop_count": 1,
        "strides": [],
        "result_type": "float"
      },
      {
        "tag": "Clamp",
        "dst": 43,
        "args": [
          {
            "kind": "reg",
            "slot": 42,
            "scalar_type": "float"
          },
          {
            "kind": "const",
            "val": 0,
            "scalar_type": "float"
          },
          {
            "kind": "const",
            "val": 1,
            "scalar_type": "float"
          }
        ],
        "loop_count": 1,
        "strides": [],
        "result_type": "float"
      },
      {
        "tag": "Add",
        "dst": 44,
        "args": [
          {
            "kind": "reg",
            "slot": 43,
            "scalar_type": "float"
          },
          {
            "kind": "const",
            "val": 0,
            "scalar_type": "float"
          }
        ],
        "loop_count": 1,
        "strides": [],
        "result_type": "float"
      }
    ],
    "register_count": 45,
    "array_slot_count": 1,
    "array_slot_sizes": [
      8
    ],
    "output_targets": [
      23
    ],
    "register_targets": [
      37,
      40,
      44
    ]
  }
}
